wmm2020/CMakeLists.txt
wmm2020/WMM.COF
wmm2020/__init__.py
wmm2020/base.py
wmm2020/build.py
wmm2020/meson.build
wmm2020/plots.py
wmm2020/setup.cmake
wmm2020/test_input.asc
wmm2020/this_path.py
wmm2020/wmm_cext.cp38-win_amd64.pyd
wmm2020/src/EGM9615.h
wmm2020/src/GeomagnetismHeader.h
wmm2020/src/GeomagnetismLibrary.c
wmm2020/src/wmm_cext.c
wmm2020/src/wmm_file.c
wmm2020/src/wmm_grid.c
wmm2020/src/wmm_point.c
wmm2020/src/wmm_point_sub.c
wmm2020/src/wmm_point_sub.h
wmm2020_cext-1.1.3.dist-info/LICENSE.txt
wmm2020_cext-1.1.3.dist-info/METADATA
wmm2020_cext-1.1.3.dist-info/WHEEL
wmm2020_cext-1.1.3.dist-info/top_level.txt
wmm2020_cext-1.1.3.dist-info/RECORD
