Metadata-Version: 2.1
Name: wmm2020-cext
Version: 1.1.3
Summary: WMM2020 geomagnetic model with simple object-oriented Python interface
Home-page: https://github.com/justengel/wmm2020
Author: Michael Hirsch, Ph.D.
License: UNKNOWN
Keywords: geomagnetic
Platform: UNKNOWN
Classifier: Development Status :: 5 - Production/Stable
Classifier: Environment :: Console
Classifier: Intended Audience :: Science/Research
Classifier: Operating System :: OS Independent
Classifier: Programming Language :: Python :: 3
Classifier: Topic :: Scientific/Engineering
Requires-Python: >=3.7
Requires-Dist: xarray
Requires-Dist: numpy
Provides-Extra: lint
Requires-Dist: flake8 ; extra == 'lint'
Requires-Dist: flake8-bugbear ; extra == 'lint'
Requires-Dist: flake8-builtins ; extra == 'lint'
Requires-Dist: flake8-blind-except ; extra == 'lint'
Requires-Dist: mypy ; extra == 'lint'
Provides-Extra: tests
Requires-Dist: pytest ; extra == 'tests'
